maxent_graph/MaxentGraph.py
maxent_graph/__init__.py
maxent_graph/bicm.py
maxent_graph/biecm.py
maxent_graph/bwcm.py
maxent_graph/decm.py
maxent_graph/ecm.py
maxent_graph/poibin.py
maxent_graph/rcm.py
maxent_graph/util.py
maxent_graph-0.3.1.dist-info/METADATA
maxent_graph-0.3.1.dist-info/WHEEL
maxent_graph-0.3.1.dist-info/licenses/LICENSE
maxent_graph-0.3.1.dist-info/RECORD
