Metadata-Version: 2.3
Name: maxent_graph
Version: 0.3.1
Summary: Add your description here
License-File: LICENSE
Requires-Python: >=3.12
Requires-Dist: jax>=0.4.33
Requires-Dist: networkx>=3.3
Requires-Dist: numba>=0.60.0
Requires-Dist: numpy>=2.0.2
Requires-Dist: pandas>=2.2.3
Requires-Dist: python-igraph>=0.11.6
Requires-Dist: scipy>=1.14.1
Requires-Dist: tabulate>=0.9.0
Requires-Dist: tqdm>=4.66.5
